crow/__init__.py
crow/properties.py
crow/cluster_modules/_clmm_patches.py
crow/cluster_modules/abundance.py
crow/cluster_modules/completeness_models.py
crow/cluster_modules/kernel.py
crow/cluster_modules/parameters.py
crow/cluster_modules/purity_models.py
crow/cluster_modules/shear_profile.py
crow/cluster_modules/mass_proxy/__init__.py
crow/cluster_modules/mass_proxy/gaussian_protocol.py
crow/cluster_modules/mass_proxy/murata.py
crow/integrator/__init__.py
crow/integrator/integrator.py
crow/integrator/numcosmo_integrator.py
crow/integrator/scipy_integrator.py
crow/recipes/__init__.py
crow/recipes/binned_exact.py
crow/recipes/binned_grid.py
crow/recipes/binned_parent.py
desc_crow-1.0.1.dist-info/licenses/LICENSE
desc_crow-1.0.1.dist-info/METADATA
desc_crow-1.0.1.dist-info/WHEEL
desc_crow-1.0.1.dist-info/top_level.txt
desc_crow-1.0.1.dist-info/RECORD
