Metadata-Version: 2.4
Name: desc-crow
Version: 1.0.1
Summary: Cluster Reconstruction of Observables Workbench
Author: The LSST DESC CROW Contributors
License-Expression: BSD-3-Clause
Project-URL: Homepage, https://github.com/LSSTDESC/crow
Project-URL: Repository, https://github.com/LSSTDESC/crow
Project-URL: Issues, https://github.com/LSSTDESC/crow/issues
Classifier: Development Status :: 4 - Beta
Classifier: Intended Audience :: Developers
Classifier: Intended Audience :: Science/Research
Classifier: Operating System :: MacOS
Classifier: Operating System :: POSIX :: Linux
Classifier: Programming Language :: Python
Classifier: Programming Language :: Python :: 3
Classifier: Programming Language :: Python :: 3.11
Requires-Python: >=3.11
License-File: LICENSE
Requires-Dist: clmm
Requires-Dist: numcosmo_py>=0.21.1
Requires-Dist: numpy>=2.0
Requires-Dist: pyccl>=2.8.0
Requires-Dist: scipy>=1.12
Dynamic: license-file
